monject/Connection.py
monject/ObjectManager.py
monject/Security.py
monject/__init__.py
monject/setup.py
monject-1.0.8.dist-info/licenses/LICENSE
monject-1.0.8.dist-info/METADATA
monject-1.0.8.dist-info/WHEEL
monject-1.0.8.dist-info/top_level.txt
monject-1.0.8.dist-info/RECORD
