Metadata-Version: 2.4
Name: monject
Version: 1.0.8
Summary: An Object Mapper for MongoDB
Home-page: https://github.com/Artim-Industries/monject
Author: Artim Industries
Author-email: mauritzlemgen@artim-industries.com
Classifier: Programming Language :: Python :: 3
Classifier: License :: OSI Approved :: MIT License
Classifier: Operating System :: OS Independent
Requires-Python: >=3.6
License-File: LICENSE
Dynamic: author
Dynamic: author-email
Dynamic: classifier
Dynamic: description
Dynamic: description-content-type
Dynamic: home-page
Dynamic: license-file
Dynamic: requires-python
Dynamic: summary
